swarm_py-0.1.2.dist-info/METADATA
swarm_py-0.1.2.dist-info/WHEEL
swarm_py/__init__.py
swarm_py/__init__.pyi
swarm_py/_swarm.abi3.so
swarm_py-0.1.2.dist-info/RECORD
