Metadata-Version: 2.4
Name: swarm_py
Version: 0.1.2
Classifier: Development Status :: 4 - Beta
Classifier: Intended Audience :: Science/Research
Classifier: Intended Audience :: Developers
Classifier: Programming Language :: Rust
Classifier: Programming Language :: Python :: 3
Classifier: Programming Language :: Python :: 3.10
Classifier: Programming Language :: Python :: 3.11
Classifier: Programming Language :: Python :: 3.12
Classifier: Topic :: Scientific/Engineering
Classifier: Topic :: Scientific/Engineering :: Mathematics
Classifier: Topic :: Software Development :: Libraries :: Python Modules
Summary: Fast blackbox optimisation tool written in rust, wrapped in python
Keywords: optimisation,blackbox,particle-swarm,pso,nsga,nsga2,NSGA-II,scientific-computing
Author: Aleksander Lovric <alexlovric@gmail.com>
Author-email: Aleksander Lovric <alexlovric@gmail.com>
License: MIT
Requires-Python: >=3.10
Project-URL: Source Code, https://github.com/alexlovric/swarm
